[
  {
    "id": "ai-49-aHR0cDovL2R4LmRvaS5vcmcvMTAuMzg0Ny8xNTM4LTQzNTcvYWNmYTcx",
    "nova": [
      "2024-03-01T16:51:32.203Z"
    ]
  },
  {
    "id": "0-1785792784",
    "nova": [
      "2023-12-06T06:14:28.258Z"
    ]
  },
  {
    "record": {
      "format": "E-Artikel",
      "title": "Using k-NN Artificial Intelligence for Predictive Maintenance in Facility Management",
      "contributor": [],
      "publisher": [],
      "ispartof": [],
      "identifier": "",
      "language": "Ohne Angabe",
      "subject": "",
      "description": "",
      "status": "",
      "rvk": ""
    },
    "id": "ai-49-aHR0cDovL2R4LmRvaS5vcmcvMTAuMTQ0NDUvMjM0ODgzNzkvaWplZWUtdjEwaTZwMTAx",
    "oa": 0,
    "thumbnail": "",
    "linksAccess": [
      {
        "uri": "https://www-fr.redi-bw.de/links/?rl_site=slub&amp;rl_action=link&amp;rl_link_target=oadoi&amp;rl_link_name=0&amp;rl_citation=f6f9a6bbdf221e3f448415b04caee7fe5d6d3bc70bcba922beaaf2518b9f7912&amp;PSID=8d5110892555d49244a25f70080445d6",
        "hostLabel": "... zum Aufsatz via www.internationaljournalssrg.org (Hybrid OA, CC-BY-NC-ND, gefunden durch Unpaywall) &amp;nbsp; &lt;span class=&quot;reference_oa_logo&quot;&gt;&lt;/span&gt;",
        "note": "",
        "material": "",
        "intro": ""
      }
    ],
    "copies": [],
    "parts": {},
    "nova": [
      "2023-08-16T17:35:44.607Z"
    ]
  },
  {
    "record": {
      "format": "E-Artikel",
      "title": "Usefulness of the Informant Questionnaire on Cognitive Decline in the Elderly for Predicting Postoperative Delirium in Elderly Patients: A Pilot Study",
      "contributor": [],
      "publisher": [],
      "ispartof": [],
      "identifier": "",
      "language": "Englisch",
      "subject": "General Medicine",
      "description": "",
      "status": "",
      "rvk": ""
    },
    "id": "ai-49-aHR0cDovL2R4LmRvaS5vcmcvMTAuMTI3NzkvZG5kLjIwMTUuMTQuMy4xMjA",
    "oa": 0,
    "thumbnail": "",
    "linksAccess": [
      {
        "uri": "https://www-fr.redi-bw.de/links/?rl_site=slub&amp;rl_action=link&amp;rl_link_target=ezb&amp;rl_link_name=0.article&amp;rl_citation=82a7eaf762c4394b4c70a5a3f16549e13d15fc572cb313ed9977ca510fcc89ba&amp;PSID=06a9a1ffbc38cecbcff5acd39701d9b0",
        "hostLabel": "... zum Aufsatz via dnd.or.kr",
        "note": "",
        "material": "",
        "intro": ""
      },
      {
        "uri": "https://www-fr.redi-bw.de/links/?rl_site=slub&amp;rl_action=link&amp;rl_link_target=ezb&amp;rl_link_name=issnlink&amp;rl_citation=82a7eaf762c4394b4c70a5a3f16549e13d15fc572cb313ed9977ca510fcc89ba&amp;PSID=06a9a1ffbc38cecbcff5acd39701d9b0",
        "hostLabel": "Zugangsbedingungen via EZB",
        "note": "",
        "material": "",
        "intro": ""
      }
    ],
    "copies": [],
    "parts": {},
    "nova": [
      "2023-06-14T21:49:28.273Z"
    ]
  },
  {
    "record": {
      "format": "E-Artikel",
      "title": "From Anglo American Publications",
      "contributor": [],
      "publisher": [],
      "ispartof": [],
      "identifier": "",
      "language": "Englisch",
      "subject": ["Linguistics and Language", "Language and Linguistics"],
      "description": "",
      "status": "",
      "rvk": ""
    },
    "id": "ai-49-aHR0cDovL2R4LmRvaS5vcmcvMTAuMTA4Ni80NjQ2Mzk",
    "oa": 0,
    "thumbnail": "",
    "linksAccess": [
      {
        "uri": "https://wwwdb.dbod.de/login?url=https://www-fr.redi-bw.de/links/?rl_site=slub&amp;rl_action=link&amp;rl_link_target=ezb&amp;rl_link_name=0.article&amp;rl_citation=85a30f650e56ba316586621d982ac382c460b58337570a95fd9f1c2a2cde565e&amp;PSID=fb1d6b8de9fc23eafbff76aef3e5bf97",
        "hostLabel": "... zum Aufsatz via &lt;span title=&quot;Journal STORage&quot;&gt;JSTOR&lt;/span&gt;",
        "note": "",
        "material": "",
        "intro": ""
      },
      {
        "uri": "https://www-fr.redi-bw.de/links/?rl_site=slub&amp;rl_action=link&amp;rl_link_target=ezb&amp;rl_link_name=issnlink&amp;rl_citation=85a30f650e56ba316586621d982ac382c460b58337570a95fd9f1c2a2cde565e&amp;PSID=fb1d6b8de9fc23eafbff76aef3e5bf97",
        "hostLabel": "Zugangsbedingungen via EZB",
        "note": "",
        "material": "",
        "intro": ""
      }
    ],
    "copies": [],
    "parts": {},
    "nova": [
      "2024-03-01T12:30:20.285Z"
    ]
  },
  {
    "record": {
      "format": "E-Artikel",
      "title": "Javier Espejo Sur&oacute;s y Carlos Mata Indur&aacute;in, eds., &laquo;Preludio a &quot;La dama boba&quot; de Lope de Vega (historia y cr&iacute;tica)&raquo;",
      "contributor": [],
      "publisher": [],
      "ispartof": [],
      "identifier": "",
      "language": "Ohne Angabe",
      "subject": ["Literature and Literary Theory", "Linguistics and Language", "Language and Linguistics"],
      "description": "",
      "status": "",
      "rvk": ""
    },
    "id": "ai-49-aHR0cDovL2R4LmRvaS5vcmcvMTAuNTU2NS9yZXYvYW51YXJpb2xvcGVkZXZlZ2EuNDYz",
    "oa": 0,
    "thumbnail": "",
    "linksAccess": [
      {
        "uri": "https://www-fr.redi-bw.de/links/?rl_site=slub&amp;rl_action=link&amp;rl_link_target=ezb&amp;rl_link_name=0.article&amp;rl_citation=09b780dc2f3ee444f157ae93e03236a05486c60021abba2e672a4cb66ffbc9e0&amp;PSID=7a837d20f8e2ee477613eb9848e11e81",
        "hostLabel": "... zum Aufsatz via ddd.uab.cat",
        "note": "",
        "material": "",
        "intro": ""
      },
      {
        "uri": "https://www-fr.redi-bw.de/links/?rl_site=slub&amp;rl_action=link&amp;rl_link_target=ezb&amp;rl_link_name=issnlink&amp;rl_citation=09b780dc2f3ee444f157ae93e03236a05486c60021abba2e672a4cb66ffbc9e0&amp;PSID=7a837d20f8e2ee477613eb9848e11e81",
        "hostLabel": "Zugangsbedingungen via EZB",
        "note": "",
        "material": "",
        "intro": ""
      }
    ],
    "copies": [],
    "parts": {},
    "nova": [
      "2022-11-04T16:19:31.461Z"
    ]
  },
  {
    "record": {
      "format": "E-Artikel",
      "title": "Numerical Analysis of Effective Plasma Frequency in One-Dimensional Superconducting Photonic Crystals Containing Metamaterials",
      "contributor": [],
      "publisher": [],
      "ispartof": [],
      "identifier": "",
      "language": "Englisch",
      "subject": ["Condensed Matter Physics", "Electronic, Optical and Magnetic Materials"],
      "description": "",
      "status": "",
      "rvk": ""
    },
    "id": "ai-49-aHR0cDovL2R4LmRvaS5vcmcvMTAuMTAwNy9zMTA5NDgtMDE1LTMyMTYtMQ",
    "oa": 0,
    "thumbnail": "",
    "linksAccess": [
      {
        "uri": "https://wwwdb.dbod.de/login?url=https://www-fr.redi-bw.de/links/?rl_site=slub&amp;rl_action=link&amp;rl_link_target=ezb&amp;rl_link_name=0.article&amp;rl_citation=a52dc88049a3a96b7ead17b731f35458b3bee60e89b5438e750944e65bd942a8&amp;PSID=b4aee107f000cf7b3987d4020b7fbd9e",
        "hostLabel": "... zum Aufsatz via Springer",
        "note": "",
        "material": "",
        "intro": ""
      },
      {
        "uri": "https://www-fr.redi-bw.de/links/?rl_site=slub&amp;rl_action=link&amp;rl_link_target=ezb&amp;rl_link_name=issnlink&amp;rl_citation=a52dc88049a3a96b7ead17b731f35458b3bee60e89b5438e750944e65bd942a8&amp;PSID=b4aee107f000cf7b3987d4020b7fbd9e",
        "hostLabel": "Zugangsbedingungen via EZB",
        "note": "",
        "material": "",
        "intro": ""
      }
    ],
    "copies": [],
    "parts": {},
    "nova": [
      "2023-06-15T00:02:48.655Z"
    ]
  },
  {
    "id": "ai-49-aHR0cDovL2R4LmRvaS5vcmcvMTAuMzIwODkvd2JoLnBody4yMDIwLjMoMjczKS4wMDAx",
    "nova": [
      "2023-06-14T21:44:27.457Z"
    ]
  },
  {
    "record": {
      "format": "E-Artikel",
      "title": "Does Freedom of Association Justify Restrictions on Immigration?",
      "contributor": [],
      "publisher": [],
      "ispartof": [],
      "identifier": "",
      "language": "Ohne Angabe",
      "subject": "",
      "description": "",
      "status": "",
      "rvk": ""
    },
    "id": "ai-49-aHR0cDovL2R4LmRvaS5vcmcvMTAuNzE0Ni9yYy4xMDI3MjI0",
    "oa": 0,
    "thumbnail": "",
    "linksAccess": [
      {
        "uri": "https://www-fr.redi-bw.de/links/?rl_site=slub&amp;rl_action=link&amp;rl_link_target=ezb&amp;rl_link_name=0.article&amp;rl_citation=127fb3e703fc8143d8192ad9ce33d61366c9cf40fde8e48ff883a7f2a98f1161&amp;PSID=8a47ae7390117754b701e009e0b5aac4",
        "hostLabel": "... zum Aufsatz via www.rescogitans.sdu.dk",
        "note": "",
        "material": "",
        "intro": ""
      },
      {
        "uri": "https://www-fr.redi-bw.de/links/?rl_site=slub&amp;rl_action=link&amp;rl_link_target=ezb&amp;rl_link_name=issnlink&amp;rl_citation=127fb3e703fc8143d8192ad9ce33d61366c9cf40fde8e48ff883a7f2a98f1161&amp;PSID=8a47ae7390117754b701e009e0b5aac4",
        "hostLabel": "Zugangsbedingungen via EZB",
        "note": "",
        "material": "",
        "intro": ""
      }
    ],
    "copies": [],
    "parts": {},
    "nova": [
      "2023-06-15T00:25:59.925Z"
    ]
  },
  {
    "record": {
      "format": "E-Artikel",
      "title": "Sebkezel&eacute;s az &oacute;kori Egyiptomban",
      "contributor": [],
      "publisher": [],
      "ispartof": [],
      "identifier": "",
      "language": "Ohne Angabe",
      "subject": ["General Earth and Planetary Sciences", "General Environmental Science"],
      "description": "",
      "status": "",
      "rvk": ""
    },
    "id": "ai-49-aHR0cDovL2R4LmRvaS5vcmcvMTAuMTcxMDcva2guMjAyMi4yNC4yNC0zNA",
    "oa": 0,
    "thumbnail": "",
    "linksAccess": [
      {
        "uri": "https://www-fr.redi-bw.de/links/?rl_site=slub&amp;rl_action=link&amp;rl_link_target=ezb&amp;rl_link_name=0.article&amp;rl_citation=4f1563c69326fbb07fe1b9629211f48b5e286e941bd1c4b76c6e91f82a80ee70&amp;PSID=a6283fc7964b6e85e3e114da75098883",
        "hostLabel": "... zum Aufsatz via www.kaleidoscopehistory.hu",
        "note": "",
        "material": "",
        "intro": ""
      },
      {
        "uri": "https://www-fr.redi-bw.de/links/?rl_site=slub&amp;rl_action=link&amp;rl_link_target=ezb&amp;rl_link_name=issnlink&amp;rl_citation=4f1563c69326fbb07fe1b9629211f48b5e286e941bd1c4b76c6e91f82a80ee70&amp;PSID=a6283fc7964b6e85e3e114da75098883",
        "hostLabel": "Zugangsbedingungen via EZB",
        "note": "",
        "material": "",
        "intro": ""
      },
      {
        "uri": "https://www-fr.redi-bw.de/links/?rl_site=slub&amp;rl_action=link&amp;rl_link_target=oadoi&amp;rl_link_name=0&amp;rl_citation=4f1563c69326fbb07fe1b9629211f48b5e286e941bd1c4b76c6e91f82a80ee70&amp;PSID=a6283fc7964b6e85e3e114da75098883",
        "hostLabel": "... zum Aufsatz via &lt;span title=&quot;Digital Object Identifier&quot;&gt;DOI&lt;/span&gt; (Gold OA, gefunden durch Unpaywall) &amp;nbsp; &lt;span class=&quot;reference_oa_logo&quot;&gt;&lt;/span&gt;",
        "note": "",
        "material": "",
        "intro": ""
      }
    ],
    "copies": [],
    "parts": {},
    "nova": [
      "2022-09-12T18:07:37.459Z"
    ]
  }
]
